{"YouTube":{"color":{"red":8186733,"orange":7721280,"yellow":7945915,"green":7665762,"purple":8097938,"orange-red":8183483,"yellow-orange":7366281,"yellow-green":7714619,"blue-green":8049576,"blue-purple":8009449,"red-purple":7837427,"achromatic":7564534,"blue":8182456}},"Twitter":{"color":{"red":5028822,"orange":2230522,"yellow":2658522,"green":1378499,"purple":4066022,"orange-red":2833822,"yellow-orange":2230522,"yellow-green":2234822,"blue-green":2141199,"blue-purple":3783022,"red-purple":5040222,"achromatic":1074699,"blue":2698022}},"Facebook":{"color":{"red":812633,"orange":649233,"yellow":451047,"green":42619,"purple":185931,"orange-red":812633,"yellow-orange":479376,"yellow-green":37581,"blue-green":195975,"blue-purple":176008,"red-purple":604403,"achromatic":29912,"blue":171101}},"Instagram":{"color":{"red":133056130,"orange":117616348,"yellow":84980758,"green":49521161,"purple":92996429,"orange-red":118420992,"yellow-orange":104119483,"yellow-green":61953396,"blue-green":97652862,"blue-purple":91858420,"red-purple":100865396,"achromatic":30553068,"blue":100251687}}}